{
  "id": "a8837c30-801a-45b6-b305-0c45e8ed1d44",
  "title": "Maximum Number of Words You Can Type",
  "slug": "maximum-number-of-words-you-can-type",
  "description": "There is a malfunctioning keyboard where some letter keys do not work. All other keys on the keyboard work properly.\n\nGiven a string `text` of words separated by a single space (no leading or trailing spaces) and a string `brokenLetters` of all **distinct** letter keys that are broken, return _the **number of words** in_ `text` _you can fully type using this keyboard_.\n\n**Example 1:**\n\n**Input:** text =  \"hello world \", brokenLetters =  \"ad \"\n**Output:** 1\n**Explanation:** We cannot type  \"world \" because the 'd' key is broken.\n\n**Example 2:**\n\n**Input:** text =  \"leet code \", brokenLetters =  \"lt \"\n**Output:** 1\n**Explanation:** We cannot type  \"leet \" because the 'l' and 't' keys are broken.\n\n**Example 3:**\n\n**Input:** text =  \"leet code \", brokenLetters =  \"e \"\n**Output:** 0\n**Explanation:** We cannot type either word because the 'e' key is broken.\n\n**Constraints:**\n\n*   `1 <= text.length <= 104`\n*   `0 <= brokenLetters.length <= 26`\n*   `text` consists of words separated by a single space without any leading or trailing spaces.\n*   Each word only consists of lowercase English letters.\n*   `brokenLetters` consists of **distinct** lowercase English letters.",
  "difficulty": "Easy",
  "category": null,
  "xpReward": 0,
  "timeLimitMs": 5000,
  "memoryLimitMb": 256,
  "starterCode": {},
  "solutionCode": "",
  "hints": [],
  "isPremium": false,
  "createdBy": null,
  "testCases": [
    {
      "input": [
        "hello world ",
        "ad "
      ],
      "expectedOutput": 1
    },
    {
      "input": [
        "leet code ",
        "lt "
      ],
      "expectedOutput": 1
    },
    {
      "input": [
        "leet code ",
        "e "
      ],
      "expectedOutput": 0
    }
  ],
  "hiddenTestCases": [
    {
      "input": [
        "hello world ",
        "ad "
      ],
      "expectedOutput": 1
    },
    {
      "input": [
        "leet code ",
        "lt "
      ],
      "expectedOutput": 1
    }
  ],
  "tags": [],
  "constraints": [],
  "examples": [],
  "problemNumber": null,
  "createdAt": "2025-11-14T21:23:43.626982+00:00",
  "updatedAt": "2025-12-04T04:36:31.884Z"
}
